py_file_meta/__init__.py
py_file_meta/file_meta.cpython-39-darwin.so
py_file_meta-0.1.0.dist-info/LICENSE
py_file_meta-0.1.0.dist-info/METADATA
py_file_meta-0.1.0.dist-info/WHEEL
py_file_meta-0.1.0.dist-info/top_level.txt
py_file_meta-0.1.0.dist-info/RECORD
