Metadata-Version: 2.1
Name: py_file_meta
Version: 0.1.0
Summary: 用于解析文件的元数据，如果是markdown，则进一步提取文件属性
Home-page: https://github.com/al6nlee/PyFileMeta
Author: alan
Author-email: al6nlee@gmail.com
License: MIT License
Classifier: Intended Audience :: Developers
Classifier: License :: OSI Approved :: MIT License
Classifier: Programming Language :: Python :: 3
Classifier: Topic :: Software Development
Requires-Python: >=3.8
License-File: LICENSE
Requires-Dist: pyyaml
